<?xml version="1.0" encoding="UTF-8"?>
<play xmlns="http://lina.digital">
    <header>
        <title>MÉDÉE</title>
        <subtitle>TRAGÉDIE</subtitle>
        <genretitle>Tragédie</genretitle>
        <author>CORNEILLE, Pierre</author>
        <date when="1634">1634</date>
        <source>https://github.com/dramacode/theatre-classique/CORNEILLEP_MEDEE.xml</source>
    </header>
    <personae>
        <character>
            <name>pollux</name>
            <alias xml:id="pollux">
                <name>pollux</name>
                <sex>m</sex>
            </alias>
        </character>
        <character>
            <name>jason</name>
            <alias xml:id="jason">
                <name>jason</name>
                <sex>m</sex>
            </alias>
        </character>
        <character>
            <name>c_use</name>
            <alias xml:id="c_use">
                <name>c_use</name>
                <sex>f</sex>
            </alias>
        </character>
        <character>
            <name>cleone</name>
            <alias xml:id="cleone">
                <name>cleone</name>
            </alias>
        </character>
        <character>
            <name>__e</name>
            <alias xml:id="__e">
                <name>__e</name>
                <sex>f</sex>
            </alias>
        </character>
        <character>
            <name>nerine</name>
            <alias xml:id="nerine">
                <name>nerine</name>
            </alias>
        </character>
        <character>
            <name>c_on</name>
            <alias xml:id="c_on">
                <name>c_on</name>
                <sex>m</sex>
            </alias>
        </character>
        <character>
            <name>aegee</name>
            <alias xml:id="aegee">
                <name>aegee</name>
            </alias>
        </character>
        <character>
            <name>theudas</name>
            <alias xml:id="theudas">
                <name>theudas</name>
                <sex>m</sex>
            </alias>
        </character>
    </personae>
    <text>
        <div>
            <head>ACTE I</head>
            <div>
                <head>SCÈNE PREMIÈRE. Pollux, Jason.</head>
                <sp who="#pollux">
                    <amount n="12" unit="speech_acts"/>
                    <amount n="424" unit="words"/>
                    <amount n="56" unit="lines"/>
                    <amount n="2135" unit="chars"/>
                </sp>
                <sp who="#jason">
                    <amount n="11" unit="speech_acts"/>
                    <amount n="1180" unit="words"/>
                    <amount n="135" unit="lines"/>
                    <amount n="5644" unit="chars"/>
                </sp>
            </div>
            <div>
                <head>SCÈNE II.</head>
                <sp who="#jason">
                    <amount n="1" unit="speech_acts"/>
                    <amount n="155" unit="words"/>
                    <amount n="17" unit="lines"/>
                    <amount n="708" unit="chars"/>
                </sp>
            </div>
            <div>
                <head>SCÈNE III. Jason, Créuse, Cléone.</head>
                <sp who="#jason">
                    <amount n="3" unit="speech_acts"/>
                    <amount n="109" unit="words"/>
                    <amount n="14" unit="lines"/>
                    <amount n="544" unit="chars"/>
                </sp>
                <sp who="#c_use">
                    <amount n="3" unit="speech_acts"/>
                    <amount n="82" unit="words"/>
                    <amount n="11" unit="lines"/>
                    <amount n="377" unit="chars"/>
                </sp>
                <sp who="#cleone">
                    <amount n="1" unit="speech_acts"/>
                    <amount n="45" unit="words"/>
                    <amount n="6" unit="lines"/>
                    <amount n="223" unit="chars"/>
                </sp>
            </div>
            <div>
                <head>SCÈNE IV.</head>
                <sp who="#__e">
                    <amount n="1" unit="speech_acts"/>
                    <amount n="752" unit="words"/>
                    <amount n="76" unit="lines"/>
                    <amount n="3705" unit="chars"/>
                </sp>
            </div>
            <div>
                <head>SCÈNE V. Médée, Nérine.</head>
                <sp who="#__e">
                    <amount n="9" unit="speech_acts"/>
                    <amount n="477" unit="words"/>
                    <amount n="57" unit="lines"/>
                    <amount n="2177" unit="chars"/>
                </sp>
                <sp who="#nerine">
                    <amount n="9" unit="speech_acts"/>
                    <amount n="321" unit="words"/>
                    <amount n="44" unit="lines"/>
                    <amount n="1578" unit="chars"/>
                </sp>
            </div>
        </div>
        <div>
            <head>ACTE II</head>
            <div>
                <head>SCÈNE PREMIÈRE. Médée, Nérine.</head>
                <sp who="#nerine">
                    <amount n="2" unit="speech_acts"/>
                    <amount n="77" unit="words"/>
                    <amount n="10" unit="lines"/>
                    <amount n="367" unit="chars"/>
                </sp>
                <sp who="#__e">
                    <amount n="1" unit="speech_acts"/>
                    <amount n="178" unit="words"/>
                    <amount n="19" unit="lines"/>
                    <amount n="829" unit="chars"/>
                </sp>
            </div>
            <div>
                <head>SCÈNE II. Créon, Médée, Nérine, soldats.</head>
                <sp who="#c_on">
                    <amount n="9" unit="speech_acts"/>
                    <amount n="550" unit="words"/>
                    <amount n="70" unit="lines"/>
                    <amount n="2647" unit="chars"/>
                </sp>
                <sp who="#__e">
                    <amount n="8" unit="speech_acts"/>
                    <amount n="909" unit="words"/>
                    <amount n="99" unit="lines"/>
                    <amount n="4443" unit="chars"/>
                </sp>
            </div>
            <div>
                <head>SCÈNE III. Créon, Jason, Créuse, Cléone, soldats.</head>
                <sp who="#c_on">
                    <amount n="2" unit="speech_acts"/>
                    <amount n="169" unit="words"/>
                    <amount n="20" unit="lines"/>
                    <amount n="809" unit="chars"/>
                </sp>
                <sp who="#c_use">
                    <amount n="1" unit="speech_acts"/>
                    <amount n="67" unit="words"/>
                    <amount n="9" unit="lines"/>
                    <amount n="368" unit="chars"/>
                </sp>
                <sp who="#jason">
                    <amount n="1" unit="speech_acts"/>
                    <amount n="55" unit="words"/>
                    <amount n="7" unit="lines"/>
                    <amount n="275" unit="chars"/>
                </sp>
            </div>
            <div>
                <head>SCÈNE IV. Jason, Créuse, Cléone.</head>
                <sp who="#jason">
                    <amount n="3" unit="speech_acts"/>
                    <amount n="280" unit="words"/>
                    <amount n="34" unit="lines"/>
                    <amount n="1416" unit="chars"/>
                </sp>
                <sp who="#c_use">
                    <amount n="4" unit="speech_acts"/>
                    <amount n="436" unit="words"/>
                    <amount n="46" unit="lines"/>
                    <amount n="2053" unit="chars"/>
                </sp>
                <sp who="#cleone">
                    <amount n="2" unit="speech_acts"/>
                    <amount n="17" unit="words"/>
                    <amount n="4" unit="lines"/>
                    <amount n="91" unit="chars"/>
                </sp>
            </div>
            <div>
                <head>SCÈNE V. AEgée, Créuse, Cléone.</head>
                <sp who="#aegee">
                    <amount n="3" unit="speech_acts"/>
                    <amount n="335" unit="words"/>
                    <amount n="38" unit="lines"/>
                    <amount n="1588" unit="chars"/>
                </sp>
                <sp who="#c_use">
                    <amount n="2" unit="speech_acts"/>
                    <amount n="507" unit="words"/>
                    <amount n="52" unit="lines"/>
                    <amount n="2412" unit="chars"/>
                </sp>
            </div>
        </div>
        <div>
            <head>ACTE III</head>
            <div>
                <head>SCÈNE PREMIÈRE.</head>
                <sp who="#nerine">
                    <amount n="1" unit="speech_acts"/>
                    <amount n="282" unit="words"/>
                    <amount n="30" unit="lines"/>
                    <amount n="1333" unit="chars"/>
                </sp>
            </div>
            <div>
                <head>SCÈNE II. Jason, Nérine.</head>
                <sp who="#jason">
                    <amount n="3" unit="speech_acts"/>
                    <amount n="376" unit="words"/>
                    <amount n="42" unit="lines"/>
                    <amount n="1797" unit="chars"/>
                </sp>
                <sp who="#nerine">
                    <amount n="2" unit="speech_acts"/>
                    <amount n="109" unit="words"/>
                    <amount n="14" unit="lines"/>
                    <amount n="532" unit="chars"/>
                </sp>
            </div>
            <div>
                <head>SCÈNE III. Médée, Jason, Nérine.</head>
                <sp who="#__e">
                    <amount n="15" unit="speech_acts"/>
                    <amount n="1177" unit="words"/>
                    <amount n="134" unit="lines"/>
                    <amount n="5496" unit="chars"/>
                </sp>
                <sp who="#jason">
                    <amount n="15" unit="speech_acts"/>
                    <amount n="550" unit="words"/>
                    <amount n="70" unit="lines"/>
                    <amount n="2621" unit="chars"/>
                </sp>
            </div>
            <div>
                <head>SCÈNE IV. Médée, Nérine.</head>
                <sp who="#__e">
                    <amount n="4" unit="speech_acts"/>
                    <amount n="122" unit="words"/>
                    <amount n="16" unit="lines"/>
                    <amount n="568" unit="chars"/>
                </sp>
                <sp who="#nerine">
                    <amount n="3" unit="speech_acts"/>
                    <amount n="104" unit="words"/>
                    <amount n="14" unit="lines"/>
                    <amount n="493" unit="chars"/>
                </sp>
            </div>
        </div>
        <div>
            <head>ACTE IV</head>
            <div>
                <head>SCÈNE PREMIÈRE. Médée, Nérine.</head>
                <sp who="#__e">
                    <amount n="5" unit="speech_acts"/>
                    <amount n="823" unit="words"/>
                    <amount n="78" unit="lines"/>
                    <amount n="3924" unit="chars"/>
                </sp>
                <sp who="#nerine">
                    <amount n="4" unit="speech_acts"/>
                    <amount n="327" unit="words"/>
                    <amount n="37" unit="lines"/>
                    <amount n="1565" unit="chars"/>
                </sp>
            </div>
            <div>
                <head>SCÈNE II. Créon, Pollux, soldats.</head>
                <sp who="#c_on">
                    <amount n="5" unit="speech_acts"/>
                    <amount n="308" unit="words"/>
                    <amount n="38" unit="lines"/>
                    <amount n="1504" unit="chars"/>
                </sp>
                <sp who="#pollux">
                    <amount n="4" unit="speech_acts"/>
                    <amount n="222" unit="words"/>
                    <amount n="29" unit="lines"/>
                    <amount n="1138" unit="chars"/>
                </sp>
            </div>
            <div>
                <head>SCÈNE III. Créon, Pollux, Cléone.</head>
                <sp who="#c_on">
                    <amount n="6" unit="speech_acts"/>
                    <amount n="152" unit="words"/>
                    <amount n="23" unit="lines"/>
                    <amount n="769" unit="chars"/>
                </sp>
                <sp who="#cleone">
                    <amount n="3" unit="speech_acts"/>
                    <amount n="143" unit="words"/>
                    <amount n="20" unit="lines"/>
                    <amount n="741" unit="chars"/>
                </sp>
                <sp who="#pollux">
                    <amount n="4" unit="speech_acts"/>
                    <amount n="179" unit="words"/>
                    <amount n="21" unit="lines"/>
                    <amount n="852" unit="chars"/>
                </sp>
            </div>
            <div>
                <head>SCÈNE IV.</head>
                <sp who="#aegee">
                    <amount n="1" unit="speech_acts"/>
                    <amount n="398" unit="words"/>
                    <amount n="57" unit="lines"/>
                    <amount n="1929" unit="chars"/>
                </sp>
            </div>
            <div>
                <head>SCÈNE V. AEgée, Médée.</head>
                <sp who="#aegee">
                    <amount n="5" unit="speech_acts"/>
                    <amount n="388" unit="words"/>
                    <amount n="47" unit="lines"/>
                    <amount n="1936" unit="chars"/>
                </sp>
                <sp who="#__e">
                    <amount n="4" unit="speech_acts"/>
                    <amount n="448" unit="words"/>
                    <amount n="50" unit="lines"/>
                    <amount n="2132" unit="chars"/>
                </sp>
            </div>
        </div>
        <div>
            <head>ACTE V</head>
            <div>
                <head>SCÈNE PREMIÈRE. Médée, Theudas.</head>
                <sp who="#theudas">
                    <amount n="5" unit="speech_acts"/>
                    <amount n="287" unit="words"/>
                    <amount n="35" unit="lines"/>
                    <amount n="1414" unit="chars"/>
                </sp>
                <sp who="#__e">
                    <amount n="5" unit="speech_acts"/>
                    <amount n="58" unit="words"/>
                    <amount n="11" unit="lines"/>
                    <amount n="279" unit="chars"/>
                </sp>
            </div>
            <div>
                <head>SCÈNE II.</head>
                <sp who="#__e">
                    <amount n="1" unit="speech_acts"/>
                    <amount n="333" unit="words"/>
                    <amount n="34" unit="lines"/>
                    <amount n="1543" unit="chars"/>
                </sp>
            </div>
            <div>
                <head>SCÈNE III. Créon, domestiques.</head>
                <sp who="#c_on">
                    <amount n="1" unit="speech_acts"/>
                    <amount n="168" unit="words"/>
                    <amount n="19" unit="lines"/>
                    <amount n="779" unit="chars"/>
                </sp>
            </div>
            <div>
                <head>SCÈNE IV. Créon, Créuse, Cléone.</head>
                <sp who="#c_use">
                    <amount n="5" unit="speech_acts"/>
                    <amount n="331" unit="words"/>
                    <amount n="40" unit="lines"/>
                    <amount n="1567" unit="chars"/>
                </sp>
                <sp who="#c_on">
                    <amount n="3" unit="speech_acts"/>
                    <amount n="281" unit="words"/>
                    <amount n="32" unit="lines"/>
                    <amount n="1280" unit="chars"/>
                </sp>
                <sp who="#cleone">
                    <amount n="2" unit="speech_acts"/>
                    <amount n="91" unit="words"/>
                    <amount n="11" unit="lines"/>
                    <amount n="411" unit="chars"/>
                </sp>
            </div>
            <div>
                <head>SCÈNE V. Jason, Créuse, Cléone, Theudas.</head>
                <sp who="#jason">
                    <amount n="3" unit="speech_acts"/>
                    <amount n="834" unit="words"/>
                    <amount n="77" unit="lines"/>
                    <amount n="4020" unit="chars"/>
                </sp>
                <sp who="#c_use">
                    <amount n="2" unit="speech_acts"/>
                    <amount n="274" unit="words"/>
                    <amount n="29" unit="lines"/>
                    <amount n="1213" unit="chars"/>
                </sp>
            </div>
            <div>
                <head>SCÈNE VI. Médée, Jason.</head>
                <sp who="#__e">
                    <amount n="4" unit="speech_acts"/>
                    <amount n="375" unit="words"/>
                    <amount n="40" unit="lines"/>
                    <amount n="1727" unit="chars"/>
                </sp>
                <sp who="#jason">
                    <amount n="3" unit="speech_acts"/>
                    <amount n="87" unit="words"/>
                    <amount n="12" unit="lines"/>
                    <amount n="411" unit="chars"/>
                </sp>
            </div>
            <div>
                <head>SCÈNE VII.</head>
                <sp who="#jason">
                    <amount n="1" unit="speech_acts"/>
                    <amount n="487" unit="words"/>
                    <amount n="52" unit="lines"/>
                    <amount n="2365" unit="chars"/>
                </sp>
            </div>
        </div>
    </text>
</play>