<?xml version="1.0" encoding="UTF-8"?>
<play xmlns="http://lina.digital" id="386tc">
    <header>
        <title>ALCIMEDON</title>
        <subtitle>TRAGI-COMÉDIE</subtitle>
        <genretitle>Tragi-comédie</genretitle>
        <author>DU RYER, Pierre</author>
        <date type="premiere" when="1635">1635</date>
        <date type="print" when="1636">1636</date>
        <source>https://github.com/dramacode/theatre-classique/DURYER_ALCIMEDON.xml</source>
    </header>
    <personae>
        <character>
            <name>NÉRINE</name>
            <alias xml:id="nerine">
                <name>NÉRINE</name>
                <sex>f</sex>
            </alias>
        </character>
        <character>
            <name>DAPHNÉ</name>
            <alias xml:id="daphne">
                <name>DAPHNÉ</name>
                <sex>f</sex>
            </alias>
        </character>
        <character>
            <name>PHILANTE</name>
            <alias xml:id="philante">
                <name>PHILANTE</name>
                <sex>m</sex>
            </alias>
        </character>
        <character>
            <name>SCAMANDRE</name>
            <alias xml:id="scamandre">
                <name>SCAMANDRE</name>
                <sex>m</sex>
            </alias>
        </character>
        <character>
            <name>RODOPE</name>
            <alias xml:id="rodope">
                <name>RODOPE</name>
                <sex>f</sex>
            </alias>
        </character>
        <character>
            <name>TIRÈNE</name>
            <alias xml:id="tirene">
                <name>TIRÈNE</name>
                <sex>m</sex>
            </alias>
        </character>
        <character>
            <name>TRACINE</name>
            <alias xml:id="tracine">
                <name>TRACINE</name>
                <sex>m</sex>
            </alias>
        </character>
        <character>
            <name>GÉRON</name>
            <alias xml:id="geron">
                <name>GÉRON</name>
                <sex>m</sex>
            </alias>
        </character>
    </personae>
    <text>
        <div>
            <head>ACTE I</head>
            <div>
                <head>SCÈNE PREMIÈRE. Nérine, Daphné.</head>
                <sp who="#nerine">
                    <amount n="19" unit="speech_acts"/>
                    <amount n="980" unit="words"/>
                    <amount n="131" unit="lines"/>
                    <amount n="5032" unit="chars"/>
                </sp>
                <sp who="#daphne">
                    <amount n="19" unit="speech_acts"/>
                    <amount n="836" unit="words"/>
                    <amount n="110" unit="lines"/>
                    <amount n="4060" unit="chars"/>
                </sp>
            </div>
            <div>
                <head>SCÈNE II. Philante, Daphné, Scamandre, Nérine.</head>
                <sp who="#philante">
                    <amount n="2" unit="speech_acts"/>
                    <amount n="16" unit="words"/>
                    <amount n="6" unit="lines"/>
                    <amount n="80" unit="chars"/>
                </sp>
                <sp who="#scamandre">
                    <amount n="4" unit="speech_acts"/>
                    <amount n="346" unit="words"/>
                    <amount n="43" unit="lines"/>
                    <amount n="1731" unit="chars"/>
                </sp>
                <sp who="#nerine">
                    <amount n="6" unit="speech_acts"/>
                    <amount n="147" unit="words"/>
                    <amount n="25" unit="lines"/>
                    <amount n="772" unit="chars"/>
                </sp>
                <sp who="#daphne">
                    <amount n="5" unit="speech_acts"/>
                    <amount n="175" unit="words"/>
                    <amount n="24" unit="lines"/>
                    <amount n="837" unit="chars"/>
                </sp>
            </div>
            <div>
                <head>SCÈNE III. Nérine, Philante, Scamandre. </head>
                <sp who="#nerine">
                    <amount n="14" unit="speech_acts"/>
                    <amount n="231" unit="words"/>
                    <amount n="44" unit="lines"/>
                    <amount n="1177" unit="chars"/>
                </sp>
                <sp who="#philante">
                    <amount n="10" unit="speech_acts"/>
                    <amount n="231" unit="words"/>
                    <amount n="37" unit="lines"/>
                    <amount n="1180" unit="chars"/>
                </sp>
                <sp who="#scamandre">
                    <amount n="20" unit="speech_acts"/>
                    <amount n="742" unit="words"/>
                    <amount n="104" unit="lines"/>
                    <amount n="3675" unit="chars"/>
                </sp>
            </div>
        </div>
        <div>
            <head>ACTE II</head>
            <div>
                <head>SCÈNE PREMIÈRE. Daphné, Nérine.</head>
                <sp who="#daphne">
                    <amount n="13" unit="speech_acts"/>
                    <amount n="436" unit="words"/>
                    <amount n="65" unit="lines"/>
                    <amount n="2197" unit="chars"/>
                </sp>
                <sp who="#nerine">
                    <amount n="12" unit="speech_acts"/>
                    <amount n="283" unit="words"/>
                    <amount n="49" unit="lines"/>
                    <amount n="1475" unit="chars"/>
                </sp>
            </div>
            <div>
                <head>SCÈNE II. Scamandre, Philante, Nérine, Daphné.</head>
                <sp who="#scamandre">
                    <amount n="3" unit="speech_acts"/>
                    <amount n="244" unit="words"/>
                    <amount n="32" unit="lines"/>
                    <amount n="1281" unit="chars"/>
                </sp>
                <sp who="#philante">
                    <amount n="2" unit="speech_acts"/>
                    <amount n="71" unit="words"/>
                    <amount n="12" unit="lines"/>
                    <amount n="425" unit="chars"/>
                </sp>
                <sp who="#daphne">
                    <amount n="2" unit="speech_acts"/>
                    <amount n="21" unit="words"/>
                    <amount n="5" unit="lines"/>
                    <amount n="115" unit="chars"/>
                </sp>
                <sp who="#nerine">
                    <amount n="1" unit="speech_acts"/>
                    <amount n="39" unit="words"/>
                    <amount n="5" unit="lines"/>
                    <amount n="190" unit="chars"/>
                </sp>
            </div>
            <div>
                <head>SCÈNE III. Nérine, Daphné, Scamandre, Philante. </head>
                <sp who="#nerine">
                    <amount n="24" unit="speech_acts"/>
                    <amount n="418" unit="words"/>
                    <amount n="77" unit="lines"/>
                    <amount n="2101" unit="chars"/>
                </sp>
                <sp who="#daphne">
                    <amount n="7" unit="speech_acts"/>
                    <amount n="95" unit="words"/>
                    <amount n="19" unit="lines"/>
                    <amount n="465" unit="chars"/>
                </sp>
                <sp who="#philante">
                    <amount n="5" unit="speech_acts"/>
                    <amount n="46" unit="words"/>
                    <amount n="12" unit="lines"/>
                    <amount n="284" unit="chars"/>
                </sp>
                <sp who="#scamandre">
                    <amount n="15" unit="speech_acts"/>
                    <amount n="327" unit="words"/>
                    <amount n="58" unit="lines"/>
                    <amount n="1651" unit="chars"/>
                </sp>
            </div>
            <div>
                <head>SCÈNE IV. Scamandre, Daphné.</head>
                <sp who="#scamandre">
                    <amount n="12" unit="speech_acts"/>
                    <amount n="480" unit="words"/>
                    <amount n="68" unit="lines"/>
                    <amount n="2497" unit="chars"/>
                </sp>
                <sp who="#daphne">
                    <amount n="11" unit="speech_acts"/>
                    <amount n="285" unit="words"/>
                    <amount n="43" unit="lines"/>
                    <amount n="1450" unit="chars"/>
                </sp>
            </div>
            <div>
                <head>SCÈNE V. Rodope, Daphné, Scamandre. </head>
                <sp who="#rodope">
                    <amount n="9" unit="speech_acts"/>
                    <amount n="169" unit="words"/>
                    <amount n="32" unit="lines"/>
                    <amount n="940" unit="chars"/>
                </sp>
                <sp who="#daphne">
                    <amount n="5" unit="speech_acts"/>
                    <amount n="50" unit="words"/>
                    <amount n="12" unit="lines"/>
                    <amount n="248" unit="chars"/>
                </sp>
                <sp who="#scamandre">
                    <amount n="8" unit="speech_acts"/>
                    <amount n="220" unit="words"/>
                    <amount n="36" unit="lines"/>
                    <amount n="1131" unit="chars"/>
                </sp>
            </div>
            <div>
                <head>SCÈNE VI. Rodope, Scamandre, Daphné.</head>
                <sp who="#tirene">
                    <amount n="7" unit="speech_acts"/>
                    <amount n="178" unit="words"/>
                    <amount n="26" unit="lines"/>
                    <amount n="872" unit="chars"/>
                </sp>
                <sp who="#rodope">
                    <amount n="2" unit="speech_acts"/>
                    <amount n="16" unit="words"/>
                    <amount n="4" unit="lines"/>
                    <amount n="89" unit="chars"/>
                </sp>
                <sp who="#scamandre">
                    <amount n="1" unit="speech_acts"/>
                    <amount n="24" unit="words"/>
                    <amount n="4" unit="lines"/>
                    <amount n="140" unit="chars"/>
                </sp>
                <sp who="#daphne">
                    <amount n="5" unit="speech_acts"/>
                    <amount n="69" unit="words"/>
                    <amount n="12" unit="lines"/>
                    <amount n="338" unit="chars"/>
                </sp>
            </div>
        </div>
        <div>
            <head>ACTE III</head>
            <div>
                <head>SCÈNE PREMIÈRE. Rodope, Daphné.</head>
                <sp who="#rodope">
                    <amount n="7" unit="speech_acts"/>
                    <amount n="404" unit="words"/>
                    <amount n="48" unit="lines"/>
                    <amount n="1955" unit="chars"/>
                </sp>
                <sp who="#daphne">
                    <amount n="6" unit="speech_acts"/>
                    <amount n="174" unit="words"/>
                    <amount n="25" unit="lines"/>
                    <amount n="885" unit="chars"/>
                </sp>
            </div>
            <div>
                <head>SCÈNE II. Scamandre, Daphné, Rodope.</head>
                <sp who="#scamandre">
                    <amount n="12" unit="speech_acts"/>
                    <amount n="313" unit="words"/>
                    <amount n="50" unit="lines"/>
                    <amount n="1593" unit="chars"/>
                </sp>
                <sp who="#daphne">
                    <amount n="19" unit="speech_acts"/>
                    <amount n="375" unit="words"/>
                    <amount n="60" unit="lines"/>
                    <amount n="1847" unit="chars"/>
                </sp>
                <sp who="#rodope">
                    <amount n="13" unit="speech_acts"/>
                    <amount n="504" unit="words"/>
                    <amount n="67" unit="lines"/>
                    <amount n="2461" unit="chars"/>
                </sp>
            </div>
            <div>
                <head>SCÈNE III. Nérine, Rodope. </head>
                <sp who="#nerine">
                    <amount n="10" unit="speech_acts"/>
                    <amount n="260" unit="words"/>
                    <amount n="41" unit="lines"/>
                    <amount n="1339" unit="chars"/>
                </sp>
                <sp who="#rodope">
                    <amount n="9" unit="speech_acts"/>
                    <amount n="171" unit="words"/>
                    <amount n="29" unit="lines"/>
                    <amount n="866" unit="chars"/>
                </sp>
            </div>
            <div>
                <head>SCÈNE IV.</head>
                <sp who="#rodope">
                    <amount n="1" unit="speech_acts"/>
                    <amount n="599" unit="words"/>
                    <amount n="69" unit="lines"/>
                    <amount n="3118" unit="chars"/>
                </sp>
            </div>
        </div>
        <div>
            <head>ACTE IV</head>
            <div>
                <head>SCÈNE PREMIÈRE.</head>
                <sp who="#tirene">
                    <amount n="1" unit="speech_acts"/>
                    <amount n="193" unit="words"/>
                    <amount n="22" unit="lines"/>
                    <amount n="942" unit="chars"/>
                </sp>
            </div>
            <div>
                <head>SCÈNE II. Rodope, Tyrène.</head>
                <sp who="#rodope">
                    <amount n="12" unit="speech_acts"/>
                    <amount n="452" unit="words"/>
                    <amount n="63" unit="lines"/>
                    <amount n="2236" unit="chars"/>
                </sp>
                <sp who="#tirene">
                    <amount n="12" unit="speech_acts"/>
                    <amount n="466" unit="words"/>
                    <amount n="66" unit="lines"/>
                    <amount n="2420" unit="chars"/>
                </sp>
            </div>
            <div>
                <head>SCÈNE III. Daphné, Tyrène.</head>
                <sp who="#daphne">
                    <amount n="9" unit="speech_acts"/>
                    <amount n="139" unit="words"/>
                    <amount n="27" unit="lines"/>
                    <amount n="703" unit="chars"/>
                </sp>
                <sp who="#tirene">
                    <amount n="8" unit="speech_acts"/>
                    <amount n="246" unit="words"/>
                    <amount n="38" unit="lines"/>
                    <amount n="1259" unit="chars"/>
                </sp>
            </div>
            <div>
                <head>SCÈNE IV. Scamandre, Philante, Daphné, Tyrène.</head>
                <sp who="#scamandre">
                    <amount n="10" unit="speech_acts"/>
                    <amount n="561" unit="words"/>
                    <amount n="72" unit="lines"/>
                    <amount n="2791" unit="chars"/>
                </sp>
                <sp who="#philante">
                    <amount n="9" unit="speech_acts"/>
                    <amount n="344" unit="words"/>
                    <amount n="49" unit="lines"/>
                    <amount n="1774" unit="chars"/>
                </sp>
                <sp who="#tirene">
                    <amount n="3" unit="speech_acts"/>
                    <amount n="36" unit="words"/>
                    <amount n="8" unit="lines"/>
                    <amount n="174" unit="chars"/>
                </sp>
                <sp who="#daphne">
                    <amount n="4" unit="speech_acts"/>
                    <amount n="41" unit="words"/>
                    <amount n="10" unit="lines"/>
                    <amount n="231" unit="chars"/>
                </sp>
            </div>
            <div>
                <head>SCÈNE V. Rodope, Scamandre, Philante.</head>
                <sp who="#rodope">
                    <amount n="9" unit="speech_acts"/>
                    <amount n="520" unit="words"/>
                    <amount n="65" unit="lines"/>
                    <amount n="2488" unit="chars"/>
                </sp>
                <sp who="#scamandre">
                    <amount n="8" unit="speech_acts"/>
                    <amount n="293" unit="words"/>
                    <amount n="41" unit="lines"/>
                    <amount n="1419" unit="chars"/>
                </sp>
                <sp who="#philante">
                    <amount n="1" unit="speech_acts"/>
                    <amount n="7" unit="words"/>
                    <amount n="2" unit="lines"/>
                    <amount n="25" unit="chars"/>
                </sp>
            </div>
            <div>
                <head>SCÈNE VI. Tyrène, Rodope.</head>
                <sp who="#tirene">
                    <amount n="6" unit="speech_acts"/>
                    <amount n="83" unit="words"/>
                    <amount n="16" unit="lines"/>
                    <amount n="408" unit="chars"/>
                </sp>
                <sp who="#rodope">
                    <amount n="6" unit="speech_acts"/>
                    <amount n="174" unit="words"/>
                    <amount n="30" unit="lines"/>
                    <amount n="990" unit="chars"/>
                </sp>
            </div>
            <div>
                <head>SCÈNE VII. Tracine, Rodope.</head>
                <sp who="#tracine">
                    <amount n="5" unit="speech_acts"/>
                    <amount n="141" unit="words"/>
                    <amount n="23" unit="lines"/>
                    <amount n="723" unit="chars"/>
                </sp>
                <sp who="#rodope">
                    <amount n="5" unit="speech_acts"/>
                    <amount n="88" unit="words"/>
                    <amount n="17" unit="lines"/>
                    <amount n="461" unit="chars"/>
                </sp>
            </div>
        </div>
        <div>
            <head>ACTE V</head>
            <div>
                <head>SCÈNE PREMIÈRE. Nérine, Daphné.</head>
                <sp who="#nerine">
                    <amount n="4" unit="speech_acts"/>
                    <amount n="154" unit="words"/>
                    <amount n="21" unit="lines"/>
                    <amount n="792" unit="chars"/>
                </sp>
                <sp who="#daphne">
                    <amount n="4" unit="speech_acts"/>
                    <amount n="196" unit="words"/>
                    <amount n="26" unit="lines"/>
                    <amount n="986" unit="chars"/>
                </sp>
            </div>
            <div>
                <head>SCÈNE II. Géron, Daphné Nérine, Scamandre.</head>
                <sp who="#geron">
                    <amount n="7" unit="speech_acts"/>
                    <amount n="69" unit="words"/>
                    <amount n="17" unit="lines"/>
                    <amount n="371" unit="chars"/>
                </sp>
                <sp who="#scamandre">
                    <amount n="5" unit="speech_acts"/>
                    <amount n="155" unit="words"/>
                    <amount n="25" unit="lines"/>
                    <amount n="837" unit="chars"/>
                </sp>
                <sp who="#nerine">
                    <amount n="7" unit="speech_acts"/>
                    <amount n="111" unit="words"/>
                    <amount n="22" unit="lines"/>
                    <amount n="603" unit="chars"/>
                </sp>
                <sp who="#daphne">
                    <amount n="6" unit="speech_acts"/>
                    <amount n="318" unit="words"/>
                    <amount n="42" unit="lines"/>
                    <amount n="1608" unit="chars"/>
                </sp>
            </div>
            <div>
                <head>SCÈNE III. Tyrène, Daphné, Scamandre, Nérine.</head>
                <sp who="#tirene">
                    <amount n="7" unit="speech_acts"/>
                    <amount n="112" unit="words"/>
                    <amount n="20" unit="lines"/>
                    <amount n="522" unit="chars"/>
                </sp>
                <sp who="#scamandre">
                    <amount n="3" unit="speech_acts"/>
                    <amount n="23" unit="words"/>
                    <amount n="6" unit="lines"/>
                    <amount n="98" unit="chars"/>
                </sp>
                <sp who="#daphne">
                    <amount n="4" unit="speech_acts"/>
                    <amount n="156" unit="words"/>
                    <amount n="23" unit="lines"/>
                    <amount n="799" unit="chars"/>
                </sp>
                <sp who="#nerine">
                    <amount n="2" unit="speech_acts"/>
                    <amount n="80" unit="words"/>
                    <amount n="11" unit="lines"/>
                    <amount n="437" unit="chars"/>
                </sp>
            </div>
            <div>
                <head>SCÈNE IV. Rodope, Tracine, Daphné, Scamandre, Nérine, Tyrène.</head>
                <sp who="#rodope">
                    <amount n="6" unit="speech_acts"/>
                    <amount n="200" unit="words"/>
                    <amount n="29" unit="lines"/>
                    <amount n="1021" unit="chars"/>
                </sp>
                <sp who="#tracine">
                    <amount n="1" unit="speech_acts"/>
                    <amount n="7" unit="words"/>
                    <amount n="2" unit="lines"/>
                    <amount n="26" unit="chars"/>
                </sp>
                <sp who="#daphne">
                    <amount n="2" unit="speech_acts"/>
                    <amount n="113" unit="words"/>
                    <amount n="14" unit="lines"/>
                    <amount n="552" unit="chars"/>
                </sp>
                <sp who="#nerine">
                    <amount n="1" unit="speech_acts"/>
                    <amount n="9" unit="words"/>
                    <amount n="2" unit="lines"/>
                    <amount n="43" unit="chars"/>
                </sp>
                <sp who="#tirene">
                    <amount n="1" unit="speech_acts"/>
                    <amount n="35" unit="words"/>
                    <amount n="5" unit="lines"/>
                    <amount n="154" unit="chars"/>
                </sp>
                <sp who="#scamandre">
                    <amount n="1" unit="speech_acts"/>
                    <amount n="171" unit="words"/>
                    <amount n="21" unit="lines"/>
                    <amount n="915" unit="chars"/>
                </sp>
            </div>
            <div>
                <head>SCÈNE V. Philante, Rodope, Daphné, Scamandre, Nérine, Tyrène.</head>
                <sp who="#philante">
                    <amount n="5" unit="speech_acts"/>
                    <amount n="374" unit="words"/>
                    <amount n="49" unit="lines"/>
                    <amount n="1938" unit="chars"/>
                </sp>
                <sp who="#daphne">
                    <amount n="1" unit="speech_acts"/>
                    <amount n="21" unit="words"/>
                    <amount n="4" unit="lines"/>
                    <amount n="124" unit="chars"/>
                </sp>
                <sp who="#scamandre">
                    <amount n="2" unit="speech_acts"/>
                    <amount n="36" unit="words"/>
                    <amount n="7" unit="lines"/>
                    <amount n="208" unit="chars"/>
                </sp>
                <sp who="#tirene">
                    <amount n="2" unit="speech_acts"/>
                    <amount n="18" unit="words"/>
                    <amount n="5" unit="lines"/>
                    <amount n="95" unit="chars"/>
                </sp>
                <sp who="#rodope">
                    <amount n="3" unit="speech_acts"/>
                    <amount n="138" unit="words"/>
                    <amount n="19" unit="lines"/>
                    <amount n="687" unit="chars"/>
                </sp>
                <sp who="#nerine">
                    <amount n="1" unit="speech_acts"/>
                    <amount n="22" unit="words"/>
                    <amount n="3" unit="lines"/>
                    <amount n="93" unit="chars"/>
                </sp>
            </div>
        </div>
    </text>
</play>